digitalezorg/__init__.py
digitalezorg-0.0.1.dist-info/LICENSE
digitalezorg-0.0.1.dist-info/WHEEL
digitalezorg-0.0.1.dist-info/METADATA
digitalezorg-0.0.1.dist-info/RECORD
