Metadata-Version: 2.1
Name: digitalezorg
Version: 0.0.1
Summary: digitalezorg 
Classifier: License :: OSI Approved :: MIT License
